{
    "path": "data/raw/a20.mp3",
    "sr": 8000,
    "duration": 2508.44,
    "vad_metrics": {
        "model_info": "SileroVadModel(model=RecursiveScriptModule(\n  original_name=VADRNNJITMerge\n  (_model): RecursiveScriptModule(\n    original_name=VADRNNJIT\n    (adaptive_normalization): RecursiveScriptModule(original_name=AdaptiveAudioNormalizationNew)\n    (feature_extractor): RecursiveScriptModule(original_name=STFT)\n    (first_layer): RecursiveScriptModule(\n      original_name=Sequential\n      (0): RecursiveScriptModule(\n        original_name=ConvBlock\n        (dw_conv): RecursiveScriptModule(\n          original_name=Sequential\n          (0): RecursiveScriptModule(original_name=Conv1d)\n          (1): RecursiveScriptModule(original_name=Identity)\n          (2): RecursiveScriptModule(original_name=ReLU)\n        )\n        (pw_conv): RecursiveScriptModule(\n          original_name=Sequential\n          (0): RecursiveScriptModule(original_name=Conv1d)\n          (1): RecursiveScriptModule(original_name=Identity)\n        )\n        (proj): RecursiveScriptModule(original_name=Conv1d)\n        (activation): RecursiveScriptModule(original_name=ReLU)\n      )\n      (1): RecursiveScriptModule(original_name=Dropout)\n    )\n    (encoder): RecursiveScriptModule(\n      original_name=Sequential\n      (0): RecursiveScriptModule(original_name=Conv1d)\n      (1): RecursiveScriptModule(original_name=BatchNorm1d)\n      (2): RecursiveScriptModule(original_name=ReLU)\n      (3): RecursiveScriptModule(\n        original_name=Sequential\n        (0): RecursiveScriptModule(\n          original_name=ConvBlock\n          (dw_conv): RecursiveScriptModule(\n            original_name=Sequential\n            (0): RecursiveScriptModule(original_name=Conv1d)\n            (1): RecursiveScriptModule(original_name=Identity)\n            (2): RecursiveScriptModule(original_name=ReLU)\n          )\n          (pw_conv): RecursiveScriptModule(\n            original_name=Sequential\n            (0): RecursiveScriptModule(original_name=Conv1d)\n            (1): RecursiveScriptModule(original_name=Identity)\n          )\n          (proj): RecursiveScriptModule(original_name=Conv1d)\n          (activation): RecursiveScriptModule(original_name=ReLU)\n        )\n        (1): RecursiveScriptModule(original_name=Dropout)\n      )\n      (4): RecursiveScriptModule(original_name=Conv1d)\n      (5): RecursiveScriptModule(original_name=BatchNorm1d)\n      (6): RecursiveScriptModule(original_name=ReLU)\n      (7): RecursiveScriptModule(\n        original_name=Sequential\n        (0): RecursiveScriptModule(\n          original_name=ConvBlock\n          (dw_conv): RecursiveScriptModule(\n            original_name=Sequential\n            (0): RecursiveScriptModule(original_name=Conv1d)\n            (1): RecursiveScriptModule(original_name=Identity)\n            (2): RecursiveScriptModule(original_name=ReLU)\n          )\n          (pw_conv): RecursiveScriptModule(\n            original_name=Sequential\n            (0): RecursiveScriptModule(original_name=Conv1d)\n            (1): RecursiveScriptModule(original_name=Identity)\n          )\n          (activation): RecursiveScriptModule(original_name=ReLU)\n        )\n        (1): RecursiveScriptModule(original_name=Dropout)\n      )\n      (8): RecursiveScriptModule(original_name=Conv1d)\n      (9): RecursiveScriptModule(original_name=BatchNorm1d)\n      (10): RecursiveScriptModule(original_name=ReLU)\n      (11): RecursiveScriptModule(\n        original_name=Sequential\n        (0): RecursiveScriptModule(\n          original_name=ConvBlock\n          (dw_conv): RecursiveScriptModule(\n            original_name=Sequential\n            (0): RecursiveScriptModule(original_name=Conv1d)\n            (1): RecursiveScriptModule(original_name=Identity)\n            (2): RecursiveScriptModule(original_name=ReLU)\n          )\n          (pw_conv): RecursiveScriptModule(\n            original_name=Sequential\n            (0): RecursiveScriptModule(original_name=Conv1d)\n            (1): RecursiveScriptModule(original_name=Identity)\n          )\n          (proj): RecursiveScriptModule(original_name=Conv1d)\n          (activation): RecursiveScriptModule(original_name=ReLU)\n        )\n        (1): RecursiveScriptModule(original_name=Dropout)\n      )\n      (12): RecursiveScriptModule(original_name=Conv1d)\n      (13): RecursiveScriptModule(original_name=BatchNorm1d)\n      (14): RecursiveScriptModule(original_name=ReLU)\n    )\n    (decoder): RecursiveScriptModule(\n      original_name=VADDecoderRNNJIT\n      (rnn): RecursiveScriptModule(original_name=LSTM)\n      (decoder): RecursiveScriptModule(\n        original_name=Sequential\n        (0): RecursiveScriptModule(original_name=ReLU)\n        (1): RecursiveScriptModule(original_name=Conv1d)\n        (2): RecursiveScriptModule(original_name=Sigmoid)\n      )\n    )\n  )\n  (_model_8k): RecursiveScriptModule(\n    original_name=VADRNNJIT\n    (adaptive_normalization): RecursiveScriptModule(original_name=AdaptiveAudioNormalizationNew)\n    (feature_extractor): RecursiveScriptModule(original_name=STFT)\n    (first_layer): RecursiveScriptModule(\n      original_name=Sequential\n      (0): RecursiveScriptModule(\n        original_name=ConvBlock\n        (dw_conv): RecursiveScriptModule(\n          original_name=Sequential\n          (0): RecursiveScriptModule(original_name=Conv1d)\n          (1): RecursiveScriptModule(original_name=Identity)\n          (2): RecursiveScriptModule(original_name=ReLU)\n        )\n        (pw_conv): RecursiveScriptModule(\n          original_name=Sequential\n          (0): RecursiveScriptModule(original_name=Conv1d)\n          (1): RecursiveScriptModule(original_name=Identity)\n        )\n        (proj): RecursiveScriptModule(original_name=Conv1d)\n        (activation): RecursiveScriptModule(original_name=ReLU)\n      )\n      (1): RecursiveScriptModule(original_name=Dropout)\n    )\n    (encoder): RecursiveScriptModule(\n      original_name=Sequential\n      (0): RecursiveScriptModule(original_name=Conv1d)\n      (1): RecursiveScriptModule(original_name=BatchNorm1d)\n      (2): RecursiveScriptModule(original_name=ReLU)\n      (3): RecursiveScriptModule(\n        original_name=Sequential\n        (0): RecursiveScriptModule(\n          original_name=ConvBlock\n          (dw_conv): RecursiveScriptModule(\n            original_name=Sequential\n            (0): RecursiveScriptModule(original_name=Conv1d)\n            (1): RecursiveScriptModule(original_name=Identity)\n            (2): RecursiveScriptModule(original_name=ReLU)\n          )\n          (pw_conv): RecursiveScriptModule(\n            original_name=Sequential\n            (0): RecursiveScriptModule(original_name=Conv1d)\n            (1): RecursiveScriptModule(original_name=Identity)\n          )\n          (proj): RecursiveScriptModule(original_name=Conv1d)\n          (activation): RecursiveScriptModule(original_name=ReLU)\n        )\n        (1): RecursiveScriptModule(original_name=Dropout)\n      )\n      (4): RecursiveScriptModule(original_name=Conv1d)\n      (5): RecursiveScriptModule(original_name=BatchNorm1d)\n      (6): RecursiveScriptModule(original_name=ReLU)\n      (7): RecursiveScriptModule(\n        original_name=Sequential\n        (0): RecursiveScriptModule(\n          original_name=ConvBlock\n          (dw_conv): RecursiveScriptModule(\n            original_name=Sequential\n            (0): RecursiveScriptModule(original_name=Conv1d)\n            (1): RecursiveScriptModule(original_name=Identity)\n            (2): RecursiveScriptModule(original_name=ReLU)\n          )\n          (pw_conv): RecursiveScriptModule(\n            original_name=Sequential\n            (0): RecursiveScriptModule(original_name=Conv1d)\n            (1): RecursiveScriptModule(original_name=Identity)\n          )\n          (activation): RecursiveScriptModule(original_name=ReLU)\n        )\n        (1): RecursiveScriptModule(original_name=Dropout)\n      )\n      (8): RecursiveScriptModule(original_name=Conv1d)\n      (9): RecursiveScriptModule(original_name=BatchNorm1d)\n      (10): RecursiveScriptModule(original_name=ReLU)\n      (11): RecursiveScriptModule(\n        original_name=Sequential\n        (0): RecursiveScriptModule(\n          original_name=ConvBlock\n          (dw_conv): RecursiveScriptModule(\n            original_name=Sequential\n            (0): RecursiveScriptModule(original_name=Conv1d)\n            (1): RecursiveScriptModule(original_name=Identity)\n            (2): RecursiveScriptModule(original_name=ReLU)\n          )\n          (pw_conv): RecursiveScriptModule(\n            original_name=Sequential\n            (0): RecursiveScriptModule(original_name=Conv1d)\n            (1): RecursiveScriptModule(original_name=Identity)\n          )\n          (proj): RecursiveScriptModule(original_name=Conv1d)\n          (activation): RecursiveScriptModule(original_name=ReLU)\n        )\n        (1): RecursiveScriptModule(original_name=Dropout)\n      )\n      (12): RecursiveScriptModule(original_name=Conv1d)\n      (13): RecursiveScriptModule(original_name=BatchNorm1d)\n      (14): RecursiveScriptModule(original_name=ReLU)\n    )\n    (decoder): RecursiveScriptModule(\n      original_name=VADDecoderRNNJIT\n      (rnn): RecursiveScriptModule(original_name=LSTM)\n      (decoder): RecursiveScriptModule(\n        original_name=Sequential\n        (0): RecursiveScriptModule(original_name=ReLU)\n        (1): RecursiveScriptModule(original_name=Conv1d)\n        (2): RecursiveScriptModule(original_name=Sigmoid)\n      )\n    )\n  )\n), torch_num_threads=1)",
        "sr": 16000,
        "duration": 1856.004,
        "process_time": 122.99734920001356
    },
    "transcription_metrics": {
        "model_info": "Whisper(\n  (encoder): AudioEncoder(\n    (conv1): Conv1d(80, 1024, kernel_size=(3,), stride=(1,), padding=(1,))\n    (conv2): Conv1d(1024, 1024, kernel_size=(3,), stride=(2,), padding=(1,))\n    (blocks): ModuleList(\n      (0-23): 24 x ResidualAttentionBlock(\n        (attn): MultiHeadAttention(\n          (query): Linear(in_features=1024, out_features=1024, bias=True)\n          (key): Linear(in_features=1024, out_features=1024, bias=False)\n          (value): Linear(in_features=1024, out_features=1024, bias=True)\n          (out): Linear(in_features=1024, out_features=1024, bias=True)\n        )\n        (attn_ln): LayerNorm((1024,), eps=1e-05, elementwise_affine=True)\n        (mlp): Sequential(\n          (0): Linear(in_features=1024, out_features=4096, bias=True)\n          (1): GELU(approximate='none')\n          (2): Linear(in_features=4096, out_features=1024, bias=True)\n        )\n        (mlp_ln): LayerNorm((1024,), eps=1e-05, elementwise_affine=True)\n      )\n    )\n    (ln_post): LayerNorm((1024,), eps=1e-05, elementwise_affine=True)\n  )\n  (decoder): TextDecoder(\n    (token_embedding): Embedding(51865, 1024)\n    (blocks): ModuleList(\n      (0-23): 24 x ResidualAttentionBlock(\n        (attn): MultiHeadAttention(\n          (query): Linear(in_features=1024, out_features=1024, bias=True)\n          (key): Linear(in_features=1024, out_features=1024, bias=False)\n          (value): Linear(in_features=1024, out_features=1024, bias=True)\n          (out): Linear(in_features=1024, out_features=1024, bias=True)\n        )\n        (attn_ln): LayerNorm((1024,), eps=1e-05, elementwise_affine=True)\n        (cross_attn): MultiHeadAttention(\n          (query): Linear(in_features=1024, out_features=1024, bias=True)\n          (key): Linear(in_features=1024, out_features=1024, bias=False)\n          (value): Linear(in_features=1024, out_features=1024, bias=True)\n          (out): Linear(in_features=1024, out_features=1024, bias=True)\n        )\n        (cross_attn_ln): LayerNorm((1024,), eps=1e-05, elementwise_affine=True)\n        (mlp): Sequential(\n          (0): Linear(in_features=1024, out_features=4096, bias=True)\n          (1): GELU(approximate='none')\n          (2): Linear(in_features=4096, out_features=1024, bias=True)\n        )\n        (mlp_ln): LayerNorm((1024,), eps=1e-05, elementwise_affine=True)\n      )\n    )\n    (ln): LayerNorm((1024,), eps=1e-05, elementwise_affine=True)\n  )\n)",
        "sr": 16000,
        "transcription": " que eu faço por aqui, fica gravado dentro do Nectar. Deixa eu ver aqui. Chamando aqui. É. Oi, William. Tá me ouvindo? Beleza. Cara, vamos lá. O Aramis marcou essa call com a gente para semana passada, mas eu acho que você estava bem corrido por aí, até por ser de fechamento de mês e não conseguiu. Mas vamos lá. Você tá me ouvindo bem? Tô te ouvindo bem. Beleza, tá bom. Então vamos lá. A questão que a gente passou da MW é que dentro da parte comercial da empresa, da operação comercial, você está encontrando dificuldade para gerenciar as vendas. Tanto as vendas quanto o trabalho dos colaboradores, e aí manter uma centralização de informação saudável. Isso não está acontecendo até porque vocês estão usando planilha para gerenciar essas oportunidades. Pelo que eu sei. Eu tenho uma equipe de venda de 20 pessoas. Nós somos uma empresa bem pequena. Então o que acontece? Eu tenho que acompanhar toda a projeção de contato do vendedor desde da primeira proposta do INVID, de uma presença. Para quê? Até para não cair no conflito de outro representante estar trabalhando o mesmo cliente. Então isso está acontecendo. E outro ponto é o que? Esse é um ponto. Então é não gerar conflito entre os representantes. Eu estou monitorando isso. O segundo ponto é, por exemplo, um representante começou a fazer um trabalho no cliente. Passou dois meses, três meses, não teve uma centralização, esse cliente fica livre depois. Então é também controlar isso. Controlar também quem fez as vendas, quando que a data foi recebida, o cliente ou o representante. Até para ele também. E eu estou tendo muita atividade para fazer isso. É, é mentir. Tá, só um mentir. Você falou que não quer que o representante trabalhe o lixo do outro. Esse é um ponto. O outro ponto... O seu sistema não vai fazer isso. Então, por exemplo, eu só preciso saber. Por exemplo, o representante João está fazendo trabalho na botarantinha. Então se alguém for fazer um trabalho na botarantinha, eu já vou criar uma observação. Não é para entrar na botarantinha porque o João já está fazendo trabalho lá. Entendi. Na verdade, o Nectar tem os níveis de permissões. Então se você quiser restringir a base por usuário, sem deixar que uma pessoa veja as oportunidades ou contatos de outro vendedor, é possível fazer isso. Até restringir a criação de contatos com o mesmo nome ou mesmo CNPJ para que ele não crie esse contato em duplicidade. Então tem como fazer essas configurações e personalizar isso para o cenário de vocês, tá bom? A transferência de responsabilidade é como... É dois meses que você falou, né? Isso já é um parâmetro que vocês definiram ou você deu um exemplo só? É um exemplo, porque, por exemplo, a gente vai colocar dois meses. Aí suponhando isso, por exemplo, eu vou lá, faço uma apresentação e a gente fala olha, eu vou comprar, só que eu só vou colocar no budget. O cliente é meu, então aí ele vai ficar travado. Entendi. Vamos lá. Vamos lá. Sobre essa transferência de responsabilidade, você consegue filtrar os contatos que não foram atualizados. Então a gente consegue ver os contatos que não foram movimentados porque não houve atualização, né? Não houve mudança de status ou de ciclo de vida ou de campos cadastrais ou então até mesmo de FEC. A gente consegue filtrar esses contatos e por período. Então se em dois meses eu filtrar contatos e eu ver que esses contatos não foram atualizados pela pessoa tal, eu deixo na minha responsabilidade de gestor. E aí eu vejo quem está com menos contatos ou quem está fazendo um bom trabalho e distribui esses leads, tá? A gente tem até um... Está no nosso roadmap para esse ano desenvolver o workflow de responsabilidade. Então, por exemplo, a gente define um parâmetro, um período de até quanto tempo um contato pode ficar na permissão de um usuário. Então se aquele usuário não atualizar o contato, automaticamente o Nectar transfere a pessoa. Então a gente está... A gente quer desenvolver isso ainda nesse ano, tá? É para ser de forma automática, mas aí de forma manual você consegue ter esse controle. E sobre o terceiro ponto, cara, eu quero anotar. Você pode falar para mim qual que é o terceiro ponto que você pretende melhorar aí? Você falou três coisas, eu anotei todas. Eu falei... Tá, pera aí, eu falei do primeiro contato. Escrevendo o ponto eu preciso gerenciar o terceiro ponto, gerenciar as vendas que foram concretizadas, entendeu? Qual que vai ser a data de recebimento do cliente e o representante já se programar a data que ele vai receber à cliente? Data de recebimento do cliente. Sobre isso a gente consegue fazer uma criação de um campo personalizado dentro da oportunidade ou do próprio contato ou até quando o vendedor preenche um formulário de perguntas e respostas para ajudar ele a qualificar aquele lead, essa resposta já vai responder essa pergunta aí. Qual que é a data de recebimento do cliente? Isso pode ser feito como campo personalizado, até para alguém do financeiro ou alguma pessoa que é responsável pelas faturas, por enviar o boleto ser notificado pelo próprio vendedor para que essa pessoa possa enviar as comissões. Mas assim, sobre controle de faturamento, de envio de boleto, né? O cliente não faz isso, tá? Não, não, não, não, não. Eu preciso de enviar boleto, não. Tanto que eu nem quero entrar em personalização, cara. Nós somos uma empresa pequena, a gente está em ascendente de crescimento. Então, assim, é mais assim, eu saber, se tiver um campo de observação, a venda concretizada, eu colocar, precisa, não haverá nem nada, gerar boleto, algo, algo. Tá bom, beleza. Sobre a MW, eu vi que no site de vocês, que vocês trabalham com equipamentos tecnológicos de segurança, né? Isso. Deixa eu só ver aqui, estou vendo alguns clientes de vocês, muito, muito clientes gigantes, hein? Muito bom. É, e está bem visualizado aí, cara. É, bem visualizado. É, a gente hoje está, quase clientes do Brasil, tá? Pegando contrato agora assim. Uambé, Rotorantim, Petrobras, enfim. É que a gente está fazendo no nosso site. Muito bom. E quanto que vai ser o nosso site de vocês? Ah, cara, daqui uns dois meses. Ah, maravilhoso, maravilhoso. E sobre site, até falando de um passo antes das vendas, como que está o trabalho do marketing de vocês aí, interno? Ah, cara, ainda não está, assim, tem nada de cliente, não. Não tem nenhuma ferramenta para automação. Mas do marketing, do quê? De divulgação ou tal? Hoje em dia tem ferramentas que permitem elaborar estratégias de marketing para os leads de vocês. Até mesmo os leads podem entrar no site, preencher um formulário ali mesmo, esse lead pode cair dentro de um fluxo de nutrição, dentro de uma ferramenta. E aí quando esse cara for bem nutrido, levantar a mão, ele é jogado diretamente para o CRM, entendeu? Isso aí eu tenho, só que isso aí vai ser o segundo passo. Ah, entendi, futuro, né? É como a gente está começando a ter muita venda, assim, eu primeiro preciso ajeitar isso aí, aí depois eu vou ter mais tranquilidade para ver também, para onde suma. Entendi. Hoje, como que você faz a captura dos leads? Cara, é hoje, dos clientes, você disse? Exatamente. Para iniciar um processo de prospecção ou você não tem prospecção aí? Não, a prospecção nossa, por exemplo, o que a gente está fazendo, tá? A gente tem parceria com os maiores distribuidores de EPIs do Brasil. Então, o que a gente faz? Geralmente eles fazem esse marketing, a lista de leads que eles têm, e aí vai um representante, que é a tendência, e ele faz visita, entendeu? Então a gente trabalha mais com presencial praticamente, o vendedor ele vai, faz visita, ele tem o equipamento, ele faz demonstração, ele deixa em teste, entendeu? Ele é todo unido aí de equipamentos físicos, né? Não sei se eu respondi a sua pergunta. Respondeu, respondeu. Geralmente, o que você me disse é que a maioria das vezes os leads que vêm para vocês são dos parceiros, né? Na verdade, da parceira que vocês têm com um dos maiores distribuidores de EPIs. Você pode falar o nome dessa parceira ou não? Tem vários, né? Tem a Banzel, Banzel Protcap EPI, tem a SP equipamentos, a Nortel. Mas são vários. É, são vários. Não, a gente tem em Brasil inteiro. Ah, então aí é muita indicação, né? É, é muita indicação. Então assim, eu prefendo depois fazer um link com eles também, porque por exemplo, essa Protcap aí, os caras têm, sei lá, mais de 200 mil CNPJ. Então ainda a gente não tem nada eficiente para monitorar isso. Entendi. Por hora não... Sobre o processo de venda de vocês, como que está estruturado ele? Você tem etapas do processo que permitem vocês seguir esse fluxo para fazer uma venda saudável? Cada vendedor tem um processo diferente? Como é que é? Não, a gente serve meio que um padrão. Por exemplo, o apresentante, ele vai até um cliente, primeiro ele faz uma dita, uma demonstração. Tá, o primeiro de tudo... Me perdoe te interromper, William. O primeiro de tudo que acontece é, esse representante pega os leads que vêm da parceria, né? É, não necessariamente da parceria, às vezes, porque ele é representante meu e ele representa outros produtos também, tipo, não, luvas, o capacete, então ele só não representa, ele não tem nas representadas dele. Então é geralmente para, tal. Então o que ele faz? Ele faz a captação de clientes, de novos clientes, de clientes que estão na rede de contato dele ou clientes que pertencem à distribuição de EPI que ele atende, do EPI que ele atende. Então é criando um contato, ou por exemplo, assim, um contato, um cliente ligou aqui para a gente, falou, eu quero tema, aí eu vejo qual região que ele está e já indica o representante fazer uma visita de acordo com a sua região. E aí o representante, ele se desloca, a gente faz uma demonstração e ele já tenta sair de lá na data para fazer um teste de equipamento, a gente, não é uma regra, a gente deixa por uma semana que é o cliente testar, né? Só que, por exemplo, a gente está, inclusive hoje, deixando em Nambeve, Bebê pediu dois equipamentos, eles querem testar 30 dias, só que é já um cliente grande, né? Então a gente acaba cedendo. E depois desses 30 dias ou uma semana de teste de acordo com o tamanho do cliente, a gente vai lá, retira o equipamento, apresenta os resultados. Caso o cliente teste com a gente, o cliente ele já emite o mando pedido de compra, a venda é feita direto pela LWT e após o recebimento do cliente, a gente repassa 800 para o representante. Esse é o ciclo, aí o ciclo com representantes é de modo de... Esse 8% é a comissão do representante. É a comissão do representante. E aí o ciclo nesse cliente com esse representante, não é que ele morre, pode ser que, naturalmente, o cliente queira comprar mais, né? Mas se o cliente comprar mais, já tá como ele fez a primeira venda, o cliente é dele, né? Então todas as futuras vendas serão... Ele fará a ajuda. Entendi, só um momentinho. Exatamente. Beleza. Você terminou de falar aí, William? Sim, sim, praticamente. Beleza. Deixa eu só confirmar, então. O que acontece é, o vendedor tem uma lista de contato dele mesmo, de network dele, ou então ele recebe pela indicação que vocês têm dos parceiros. Depois disso, ele entra em contato com essas empresas para apresentar a ferramenta de vocês e dentro dessa apresentação ele já tenta alinhar uma data para eles testarem a solução de vocês por uma ou duas ou três, dependendo do tamanho do cliente. Depois que o cliente testa, vocês vão lá e retiram a solução, ele faz um pedido de compra, depois desse pedido de compra o vendedor recebe a comissão que é de 8% e vocês recebem o restante. Se o cliente quiser comprar mais vezes, isso fica pela responsabilidade do vendedor, é isso? Não necessariamente do vendedor, assim. Por exemplo, se a gente ver que é um cliente que é pequeno e comprou uma peça, a decisão de compra vai ficar meio dependendo do cliente. Agora se é um grande para fazer uma quinição maior, aí o representante vai continuar fazendo pago ali para terminar em todas as unidades do cliente. Entendi. Você falou de uma solução ou duas soluções, qual que é o ticket médio de vocês por cliente? O ticket médio seria a quantidade de venda? Eu vou falar de uma forma mais geral, o ticket médio é o seguinte, você pega a receita total que você tem no mês e divide pela quantidade de vendas que você fez, é isso que eu quero saber, qual que é o ticket médio que vocês trabalham dentro do mês aí? Tá, então eu vou pegar o que eu faturo e divido pela quantidade de clientes que eu tenho. É, na verdade pela quantidade de vendas que você fez, porque se você dividir pela quantidade de clientes, empresas que já são clientes de vocês, vai ter um número muito pequeno, então a gente tem que dividir pela quantidade de venda. Então vamos ficar hoje, sei lá, vamos colocar aqui, nós somos uma empresa que a gente tem um método negócio inovador e até novo, então hoje nós temos quatro funcionários de um faturamento, até do ano passado, de 700 mil reais, esse ano vai, nosso faturamento vai bater dois milhões, mas eu vou considerar, só que eu não tenho aqui a relação de quantidade de vendas que a gente faz. Ah não? Não, não tenho, não tenho cara, a gente tá começando a criar um controle agora, então assim, exatamente eu não tenho. Você falou que... Assim, o que eu tenho, assim, nós já emitimos, sei lá, eu vou considerar aí pela quantidade de notas emitidas, né, então no ano passado a gente deve ter emitido umas 50 notas mais ou menos, exatamente. São poucas, né, mas é que nosso produto tem um valor agregado alto, então, sei lá, tô tirando uma média, tá, 14 mil. Beleza, beleza, 14 mil. Só que esse ano a gente já, já, já tá com isso aí já, que a gente pegou um contrato com a Vale agora, só que não é com esse produto, trato grande e tal, então vai mudar o cenário aí. Eu tô vendo aqui no site de vocês que vocês têm um, dois, três, quatro produtos principais, é, cinco, cinco produtos, né, confirma aí. É, o MW Acesso, MW Sensor, MW Visão e o Detector. É, só que quando você colocar na MW Saúde e Proteção, esse daqui é o produto tá, que a gente estourou com ele agora, então todos os vendedores nossos hoje só cuidam desse produto, que é um dispositivo que controla a utilização do creme de proteção pras mãos. Deixa eu só ver aqui rapidinho. Do lado do site? É a MW Saúde e Proteção? Não, não, do lado do site, MW Saúde e Proteção. Tô vendo, tô vendo aqui. MW Saúde. Esse é o produto que é o carro-chefe de vocês hoje? É, esse aqui é, ele entrou agora, ele tá... Hoje é só ele, a gente vai até reduzir, alguns vão tirar, alguns vão... Maravilhoso. É kit médio de 14 mil, beleza. É uma média mesmo, tá, não precisa ser tão certo não, tá, até porque como você mesmo falou, vocês começaram a gerenciar isso recentemente, então não fica tranquilo. Fica tranquilo. Agora cara, sobre o ciclo de venda de vocês, pegando pelo parâmetro que você disse, que geralmente vocês deixam a solução lá por uma semana, isso varia de acordo com o tamanho do cliente, qual que é o ciclo de venda de vocês? E eu já tô contando uma semana, então deve ter aí mais umas três semanas, você acha que em um mês vocês vendem? Como tipo, tá pegando um exemplo, um cliente, né? Exato, qualquer cliente. Ah cara, como esse produto ele é um único em Brasil, tem até patente e tal, é... Cara, um mês cara. Um mês, maravilhoso. É um mês e dois meses, entendeu? Mas tá sendo um mês cara, um mês a gente já tá com... Depois dos testes né? Sim, sim. Porque... Por que cara? Porque assim, cliente hoje ele tem uma necessidade muito, uma fragilidade, é passivo pra balismo. Então o cara tem um passivo pra balismo e a nossa tecnologia vai ligar e... Então o cara tá desabado, só que aí você pega entre os dois, olha, aí você tem que fazer um planejamento e tal. Sim, sim. Eu entendo, eu entendo. Até aqui na Nectra que vende ferramentas SaaS, né, CRM, a gente tem isso, esse diferencial também. Quando a gente fala de clientes pequenos, e eu não acho a MW iniciando a parceria com a Nectra, a gente não vai tratar vocês como cliente pequeno não, tá? Então vocês estão atendendo grandes cases do grande espelho e do mercado, isso é muito bom. Até pra chamar a atenção de pequenas, de médias e grandes empresas que vocês não atendem ainda. Então isso é muito bom. Até aqui na Nectra a gente tem um diferencial de trabalhar contas pequenas e contas grandes, né? Então quando a gente tá falando contas pequenas, geralmente a gente realiza uma venda em dez, dez dias, uma semana. Agora quando a gente fala com contas enterprise grandes, aí isso varia mais. Isso também depende da necessidade, da urgência de cada venda, né? Então isso varia bastante também. Maravilha, maravilha, William. Sobre as vendas ainda, sobre as oportunidades, quantas oportunidades vocês estão gerando dentro do mês aí na MW? Ah cara, deixa eu ver, isso aqui eu tenho um controle. Beleza, boa. Obrigado. Por mês assim é uma 50, 50 oportunidades, 50 a 80. Maravilhoso, maravilhoso. 50 a 80 porque a gente tá fazendo muito, participando de muito workshop, o que eu vou dizer, por exemplo, o desenvolvedor de EPI, ele faz um workshop lá pra falar do nosso produto, aí vai, sei lá, 300 clientes, 400, 100, uns são menores, outros 50. Então, porque esse produto acontece, ele passou por uma fase de desenvolvimento, de melhoria, e atingiu o modelo ideal pra fazer. Então, a partir do mês passado foi onde a gente começou mesmo a comercializá-lo de forma segura, então tudo isso tem de andar progressivamente. Não cara, e tá ótimo. Ter de 50 a 80 oportunidades com o ticket que vocês têm, isso é muito bom, isso é muito bom mesmo. Eu acho que vocês estão participando de eventos, de workshop agora, vocês não podem parar de participar disso. Isso está trazendo um retorno muito legal pra vocês, então continuem, se for o caso, promovam esses eventos também com os clientes de vocês que podem indicar outras empresas, isso é muito bom. Agora, falando sobre essa quantidade que você me falou, qual que é a taxa de conversão que você tem geral dentro do processo de venda? Nossa cara, aí é difícil, eu não gosto de bater isso. Por exemplo, vamos falar não de percentual, mas de quantidade, de 80 oportunidades que entram no topo do funil do processo de venda de vocês, quantas fecham? Quanto tornam o cliente? Cara, vamos colocar 10%. 10%? É, tá baixo, mas tá montando, entendeu? E o que você acha que a gente pode fazer pra melhorar essa taxa de conversão? Eu não sei, não sei ainda responder isso, porque eu preciso ter uma gestão sobre essa necessidade que eu tenho, uma visão do que está acontecendo, como que está a situação, pra eu poder ver o que pode ser feito, entendeu? Entendi. Geralmente eu vou te dizer o que acontece bastante com empresas que eu falo, líderes que eu falo diariamente, me dizem o seguinte, Guilherme, eu estou precisando de ter um controle maior de follow-up. Por quê? Dentro do processo, a gente tem esse tempo, por exemplo, de teste, trial, dependendo do serviço, né? E às vezes isso pode vender na hora, sim, o produto que você fez, mas pode esfriar também o processo. Então é muito importante, é muito relevante pra operação comercial que o vendedor compra os follow-ups e faça isso de forma assertiva. Então, a assertiva que eu falo no momento certo, não vai ficar ligando todo dia, toda hora pro cara vencer no saco dele, mas marcar com a pessoa, testa aí, mas na quarta-feira eu vou te ligar pra gente ver como é que está, se você tem alguma dúvida nessa solução aí e tal. Então, esses follow-ups ajudam bastante a manter o cara quente, né? Pra, por exemplo, uma semana, na semana que vem ele já faz o pedido da compra, a gente manda a proposta pra ele e já fecha com a gente, entendeu? E a falta disso também impacta na venda, né? Exato. Porque, por exemplo, o vendedor vai lá, faz um teste, aí não procura mais o cliente, entendeu? E aí morre. Exato, exato. Então tem isso também. E o que eu estou te falando é que, assim, agora vendendo um pouquinho o meu jabá aqui, fazendo um jabazinho, dentro do Nectar você tem a oportunidade de ter esse controle de follow-up e gerir como você vai estar por cima de quem vai estar fazendo o trabalho operacional dia a dia, você pode ver quais são as oportunidades que tem atividades atrasadas, né? Que tem compromissos que não foram registrados ou dado feedback ainda. Então, o teu controle vai ser muito profundo nisso e você vai poder cobrar dos vendedores, né? Porque você está gerindo. Então, maravilha. Isso faz sentido pra ti o que eu disse? Claro, sim, total. Maravilha. William, a última coisa, cara, desse papo que a gente tem agora, eu preciso entender como é que funciona o processo de decisão de vocês aí, interno. Está de decisão de... Para a aquisição do CRM. Qual que é? Tá. Eu vou te falar qual que é o meu próximo passo pra você ficar ciente. O meu próximo passo, a partir dessas informações que eu coletei de você e que a gente conversou aqui agora, vou preparar uma base do Nectar pra te apresentar. E uma reunião bem produtiva mesmo, bem objetiva, de 20 a 30 minutos pra gente mostrar pra te mostrar como que o Nectar vai ser útil pra vocês aí. Depois disso, eu vou... A gente vai falar de preço, tá? Se possível, na mesma reunião a gente já fala de preço e eu te apresento... Te sugiro qual que é o plano ideal pra MW. Qual que seria o plano. E eu acho que nesse primeiro momento a gente não precisa ir pro avançado. Até foi um ponto que o Aramis me briefou aqui dentro do Nectar. Ele disse que 299 por usuário não fica inviável pra vocês nesse primeiro momento. Então... Eu até concordo que a gente não precisa ir pro plano mais avançado agora, até porque dentro do que você me falou aqui a gente consegue te atender no plano mais base. Então, já pra você ter um expectativo, acho que você já teve a nossa parte de preços lá. Então, dentro do starter mesmo a gente consegue atender vocês no primeiro momento. Quando evoluir as coisas, a demanda aumentar, se precisarem de mais funcionalidade, a gente migra pra um plano mais avançado. E aí, com o passar do tempo, tem até budget pra poder fazer um investimento maior. Exatamente. De acordo com o investimento, porque, como falei, nós somos uma empresa pequena. E a gente quer se adequar, porque é isso que a gente percebeu. Eu como proprietário da empresa, o que eu estou percebendo? Cara, sem gestão não adianta eu estar tendo todas essas oportunidades, as possibilidades, mas se eu não tiver gestão eu vou quebrar, porque eu não vou estar entendendo e, enfim, é perigoso. E olha que eu estou fazendo pela dor, viu, cara? Não é pelo amor não, estou sendo bem honesto. Eu entendo, eu entendo do teu lado. Mas é pela dor que eu estou fazendo, mas eu estou bem, totalmente, decidido a fazer. Ótimo, ótimo. Me fala aí, o que a gente faz depois que eu te apresentar os preços, o Nectar, o plano, qual que é o teu próximo passo interno aí? Cara, meu próximo passo é ver o... principalmente, cara, felizmente, eu acho até triste de falar isso, né? O que vai me fazer decidir ou não vai ser o custo, porque a ferramenta de vocês não tem dúvida de que vai me entender. Então, se tiver dentro do nosso orçamento aqui, a gente já fecha de imediato já, entendeu? Tá, então deixa eu até antecipar isso contigo então, até para a gente evoluir de uma forma mais alinhada e clara possível. O plano mais básico hoje é 99 por usuário, tá? Quantas pessoas você acha que vão usar o Nectar aí? Então, o que acontece? Eu tenho representantes e representantes. Então eu tenho representantes que já tem venda, que o cara está com uma faca nos dentes, já rodando. Esses daí já vão ter de cara já. Então eu tenho 30 mais ou menos, 35, cara, é bastante gente. Só que eu não vou começar com todos. Então eu vou começar com os estratégicos e depois o pessoal vai entrando. Maravilha. Dentro do CIS do CRM de vocês, eu consigo colocar domínio de meias, essas coisas também? Sim, sim. Só que não está aí, já não é mais nesse plano básico, né? Não, no plano básico você já tem a integração com a central do G Suite, aí você pode integrar tanto o Gmail quanto o calendário da Google e fazer integração também se vocês usarem outro servidor com Outlook, tal, fazer essa integração com o Mac. Então se o vendedor tiver o domínio dele próprio, ele pode fazer essa integração com o próprio Gmail dele, tá? É, porque o que acontece? O vendedor tem geralmente, por exemplo, o MW automação arroba hotmail. Sim, sim. Então o que eu vou fazer? Eu migrei para local web aqui porque o Google é muito bom, cara. É o melhor tema que eu já vi, assim, né? Mas só que é bem caro, né, para você ter várias contas de e-mail, né, para a nossa realidade. Então eu vou fazer um e-mail para cada um, entendeu? Entendi. Não, ótimo. Isso é ótimo, o Nectar tem essa permissão, tá? Você pode fazer isso sim. Então beleza. Então você já me falou o preço. O que eu vou fazer? Você consegue me ligar na semana que vem? Oi? Você consegue me ligar na semana que vem? Consigo. A gente pode até marcar a apresentação se você estiver disponível para hoje à tarde ou para amanhã. Hoje à tarde eu vou ficar aqui na empresa, cara. Ah, maravilhoso. Se quiser, né? Se quiser me ligar, hoje é dia 6. É, me liga lá para as 16 horas. Aí essa reunião agora a gente já faz por videoconferência, que eu vou precisar compartilhar a minha tela contigo. Tá bom, beleza. Aí eu apresento o Nectar para ti. A gente já fala sobre preço, mas me dá um feedback. Você acha que esse preço de 99 por usuário é uma realidade para o teu caixa hoje? Não sei te dizer. Eu vou precisar só fazer uma conta aqui, ver como é que está, o que tem para entrar, o que tem para sair, para eu poder falar para você. Eu acho que assim, que 100 pau por mês por apresentante é um pouco pesado para a gente ainda. Tá. É um pouco pesado, porque eu estou falando de no mínimo R$2.000 por mês. Então é porque nós temos muito investimento nessa tecnologia, então fica um pouco pesado para a gente, porque a gente está fazendo um pouco de investimento. Fica um pouco pesado para a gente, transparente ainda. Só que eu não sei, eu fico preocupado da gente estar, não sei como que é o de vocês, se vocês só atendem clientes maiores, enfim, não sei. Não cara, sobre público você é perfil ideal de cliente da Nectar, já te adianto isso. Se a gente atende a tuador, e isso vai ficar claro para ti também, durante a apresentação, você é perfil, independente da quantidade de usuários. Geralmente a gente costuma, eu vou ser bem sincero, a gente costuma atender empresas que tem mais de 4 usuários. Por que de 4 usuários a gente já começa a atender. Abaixo disso a gente indica o nosso plano gratuito, porque tem ali o limite até 6 pessoas. Mas claro que tem limitações de funcionalidade. Mas para a realidade da MW, a gente inclui lá no start, no plano mais baixo, que atende assim, até se a gente apresentar nesse primeiro momento, eu vejo que atende. A gente vai confirmar isso hoje à tarde. Mas fica tranquilo, que custo é uma dor para ti também, eu vou levar isso internamente, a gente vai conversar aqui, eu vou fazer uma reunião com a minha liderança e a gente entra e ajusta um negócio bem legal para você. Tá, beleza. Qual que é a tua expectativa? Me fala aí. Cara, eu estou, sendo bem transparente, a minha expectativa é boa, porque eu preciso de sair, preciso ter controle e assim, eu tenho um, quem me indicou vocês foi um parceiro nosso que já usa. Quem que é? Ou ele usou numa outra empresa, não, ele usou numa outra empresa, ele saiu dessa empresa e ele tem uma agência. E aí ele usava, não é o seu, não é o que ele fala, ele trabalhava, ele falou muito bem e minha expectativa é boa, eu realmente assim, não é chorando as tangas não, é só a questão do custo mesmo que me preocupa, até assim, cara, daqui a dois meses, três meses, a gente já vai estar numa condição melhor, eu não consigo me readequar, entendeu? Sim, sim. Não, fica tranquilo, fica tranquilo, tá William? Fica tranquilo que a gente vai ajeitar isso aí, a gente vai iniciar essa parceria e eu quero fazer isso na semana que vem já apertar a mão contigo e a gente já iniciar a implementação com a galera que vai usar, com os vendedores estratégicos que você falou. Beleza, combinado. A gente vai ajeitar isso aí, tá bom? Tá bom então. Então a gente marca para hoje a 16, é isso? Pode ser. Então fechado. Eu vou agendar aqui, vou te enviar um invite e a gente se encontra na sala da videoconferência do Meet, do Hangout. Tá bom. Te mando o link no teu e-mail, tá bom? Beleza, combinado então. Então valeu, nesse meio tempo se você quiser falar comigo esse número que eu estou te ligando é meu número pessoal, então me chama no WhatsApp que eu estou por lá também, fica a vontade. Tá bom, combinado, beleza. Então valeu William, um grande abraço, prazer de te conhecer cara. Obrigado, igualmente. Valeu, tchau, tchau, bom dia.",
        "tokenizer_model": "gpt-3.5-turbo",
        "tokens": 8069,
        "process_time": 466.5304289999767
    }
}